NiuKeyunYinggangQiuzhiJingyanFenxiang20212022/README.md
NiuKeyunYinggangQiuzhiJingyanFenxiang20212022/__init__.py
NiuKeyunYinggangQiuzhiJingyanFenxiang20212022/__main__.py
NiuKeyunYinggangQiuzhiJingyanFenxiang20212022/file.epub
NiuKeyunYinggangQiuzhiJingyanFenxiang20212022/index.html
NiuKeyunYinggangQiuzhiJingyanFenxiang20212022/css/__init__.py
NiuKeyunYinggangQiuzhiJingyanFenxiang20212022/css/annotations.css
NiuKeyunYinggangQiuzhiJingyanFenxiang20212022/css/main.css
NiuKeyunYinggangQiuzhiJingyanFenxiang20212022/css/normalize.css
NiuKeyunYinggangQiuzhiJingyanFenxiang20212022/css/popup.css
NiuKeyunYinggangQiuzhiJingyanFenxiang20212022/font/__init__.py
NiuKeyunYinggangQiuzhiJingyanFenxiang20212022/font/fontello.eot
NiuKeyunYinggangQiuzhiJingyanFenxiang20212022/font/fontello.svg
NiuKeyunYinggangQiuzhiJingyanFenxiang20212022/font/fontello.ttf
NiuKeyunYinggangQiuzhiJingyanFenxiang20212022/font/fontello.woff
NiuKeyunYinggangQiuzhiJingyanFenxiang20212022/img/__init__.py
NiuKeyunYinggangQiuzhiJingyanFenxiang20212022/img/annotator-glyph-sprite.png
NiuKeyunYinggangQiuzhiJingyanFenxiang20212022/img/annotator-icon-sprite.png
NiuKeyunYinggangQiuzhiJingyanFenxiang20212022/img/apple-touch-icon.png
NiuKeyunYinggangQiuzhiJingyanFenxiang20212022/img/cancelfullscreen.png
NiuKeyunYinggangQiuzhiJingyanFenxiang20212022/img/close.png
NiuKeyunYinggangQiuzhiJingyanFenxiang20212022/img/fullscreen.png
NiuKeyunYinggangQiuzhiJingyanFenxiang20212022/img/loader.gif
NiuKeyunYinggangQiuzhiJingyanFenxiang20212022/img/menu-icon.png
NiuKeyunYinggangQiuzhiJingyanFenxiang20212022/img/save.png
NiuKeyunYinggangQiuzhiJingyanFenxiang20212022/img/saved.png
NiuKeyunYinggangQiuzhiJingyanFenxiang20212022/img/settings-s.png
NiuKeyunYinggangQiuzhiJingyanFenxiang20212022/img/settings.png
NiuKeyunYinggangQiuzhiJingyanFenxiang20212022/img/star.png
NiuKeyunYinggangQiuzhiJingyanFenxiang20212022/js/__init__.py
NiuKeyunYinggangQiuzhiJingyanFenxiang20212022/js/epub.js
niu_keyun_yinggang_qiuzhi_jingyan_fenxiang_2021_2022-2024.3.6.0.dist-info/METADATA
niu_keyun_yinggang_qiuzhi_jingyan_fenxiang_2021_2022-2024.3.6.0.dist-info/WHEEL
niu_keyun_yinggang_qiuzhi_jingyan_fenxiang_2021_2022-2024.3.6.0.dist-info/entry_points.txt
niu_keyun_yinggang_qiuzhi_jingyan_fenxiang_2021_2022-2024.3.6.0.dist-info/top_level.txt
niu_keyun_yinggang_qiuzhi_jingyan_fenxiang_2021_2022-2024.3.6.0.dist-info/RECORD
